terra/__init__.py
terra/activity/__init__.py
terra/activity/client.py
terra/activity/raw_client.py
terra/activity/types/__init__.py
terra/activity/types/activity_fetch_request_start_date.py
terra/activity/types/activity_fetch_response.py
terra/activity/types/activity_fetch_response_data.py
terra/activity/types/activity_write_response.py
terra/athlete/__init__.py
terra/athlete/client.py
terra/athlete/raw_client.py
terra/athlete/types/__init__.py
terra/athlete/types/athlete_fetch_response.py
terra/authentication/__init__.py
terra/authentication/client.py
terra/authentication/raw_client.py
terra/authentication/types/__init__.py
terra/authentication/types/authentication_authenticate_user_response.py
terra/authentication/types/authentication_authenticate_user_response_status.py
terra/authentication/types/authentication_deauthenticate_user_response.py
terra/authentication/types/authentication_deauthenticate_user_response_status.py
terra/authentication/types/authentication_generate_auth_token_response.py
terra/authentication/types/authentication_generate_widget_session_response.py
terra/authentication/types/authentication_generate_widget_session_response_status.py
terra/body/__init__.py
terra/body/client.py
terra/body/raw_client.py
terra/body/types/__init__.py
terra/body/types/body_delete_response.py
terra/body/types/body_delete_response_processed_data_item.py
terra/body/types/body_fetch_request_start_date.py
terra/body/types/body_fetch_response.py
terra/body/types/body_fetch_response_data.py
terra/body/types/body_write_response.py
terra/client.py
terra/core/__init__.py
terra/core/api_error.py
terra/core/client_wrapper.py
terra/core/datetime_utils.py
terra/core/file.py
terra/core/force_multipart.py
terra/core/http_client.py
terra/core/http_response.py
terra/core/jsonable_encoder.py
terra/core/pydantic_utilities.py
terra/core/query_encoder.py
terra/core/remove_none_from_dict.py
terra/core/request_options.py
terra/core/serialization.py
terra/core/unchecked_base_model.py
terra_python-1.1.0.dist-info/METADATA
terra_python-1.1.0.dist-info/WHEEL
terra_python-1.1.0.dist-info/RECORD
